curio_http/__init__.py
curio_http-0.1.0.dist-info/DESCRIPTION.rst
curio_http-0.1.0.dist-info/METADATA
curio_http-0.1.0.dist-info/metadata.json
curio_http-0.1.0.dist-info/RECORD
curio_http-0.1.0.dist-info/top_level.txt
curio_http-0.1.0.dist-info/WHEEL
