Metadata-Version: 2.0
Name: curio-http
Version: 0.1.0
Summary: Asynchronouse HTTP client based on curio.
Home-page: https://github.com/scribu/curio-http/
Author: scribu
Author-email: mail@scribu.net
License: Apache 2
Platform: UNKNOWN
Classifier: License :: OSI Approved :: Apache Software License
Classifier: Intended Audience :: Developers
Classifier: Programming Language :: Python
Classifier: Programming Language :: Python :: 3
Classifier: Programming Language :: Python :: 3.5
Classifier: Development Status :: 2 - Pre-Alpha
Classifier: Operating System :: POSIX
Classifier: Operating System :: MacOS :: MacOS X
Classifier: Topic :: Internet :: WWW/HTTP
Requires-Dist: curio (>=0.4)
Requires-Dist: h11 (>=0.6)
Requires-Dist: yarl (>=0.7)
